{
	"backtraceGraph" : 
	{
		"commands" : 
		[
			"install"
		],
		"files" : 
		[
			"lib/box2d/src/CMakeLists.txt"
		],
		"nodes" : 
		[
			{
				"file" : 0
			},
			{
				"command" : 0,
				"file" : 0,
				"line" : 193,
				"parent" : 0
			},
			{
				"command" : 0,
				"file" : 0,
				"line" : 201,
				"parent" : 0
			},
			{
				"command" : 0,
				"file" : 0,
				"line" : 207,
				"parent" : 0
			},
			{
				"command" : 0,
				"file" : 0,
				"line" : 220,
				"parent" : 0
			}
		]
	},
	"installers" : 
	[
		{
			"backtrace" : 1,
			"component" : "Unspecified",
			"destination" : "lib",
			"paths" : 
			[
				"lib/box2d/src/box2dd.lib"
			],
			"targetId" : "box2d::@9b1f8dcbf8568d3f0888",
			"targetIndex" : 1,
			"targetIsImportLibrary" : true,
			"type" : "target"
		},
		{
			"backtrace" : 1,
			"component" : "Unspecified",
			"destination" : "bin",
			"paths" : 
			[
				"lib/box2d/bin/box2dd.dll"
			],
			"targetId" : "box2d::@9b1f8dcbf8568d3f0888",
			"targetIndex" : 1,
			"type" : "target"
		},
		{
			"backtrace" : 2,
			"component" : "Unspecified",
			"destination" : "lib/cmake/box2d",
			"exportName" : "box2dConfig",
			"exportTargets" : 
			[
				{
					"id" : "box2d::@9b1f8dcbf8568d3f0888",
					"index" : 1
				}
			],
			"paths" : 
			[
				"lib/box2d/src/CMakeFiles/Export/1f7e0de6fbfb5d20e365871ec89ce73e/box2dConfig.cmake"
			],
			"type" : "export"
		},
		{
			"backtrace" : 3,
			"component" : "Unspecified",
			"destination" : "include/box2d",
			"paths" : 
			[
				"lib/box2d/src/../include/box2d/base.h",
				"lib/box2d/src/../include/box2d/box2d.h",
				"lib/box2d/src/../include/box2d/collision.h",
				"lib/box2d/src/../include/box2d/id.h",
				"lib/box2d/src/../include/box2d/math_functions.h",
				"lib/box2d/src/../include/box2d/types.h"
			],
			"type" : "file"
		},
		{
			"backtrace" : 4,
			"component" : "Unspecified",
			"destination" : "lib/cmake/box2d",
			"paths" : 
			[
				"out/build/x64-Debug/lib/box2d/src/box2dConfigVersion.cmake"
			],
			"type" : "file"
		}
	],
	"paths" : 
	{
		"build" : "lib/box2d/src",
		"source" : "lib/box2d/src"
	}
}
